{
    "/js/vue/client.js": "/js/vue/client.js",
    "/js/app.js": "/js/app.js",
    "/css/client.css": "/css/client.css",
    "/css/app.css": "/css/app.css",
    "/js/coreui.bundle.min.js": "/js/coreui.bundle.min.js",
    "/fonts/CoreUI-Icons-Brand.eot": "/fonts/CoreUI-Icons-Brand.eot",
    "/fonts/CoreUI-Icons-Brand.svg": "/fonts/CoreUI-Icons-Brand.svg",
    "/fonts/CoreUI-Icons-Brand.ttf": "/fonts/CoreUI-Icons-Brand.ttf",
    "/fonts/CoreUI-Icons-Brand.woff": "/fonts/CoreUI-Icons-Brand.woff",
    "/fonts/CoreUI-Icons-Brand.woff2": "/fonts/CoreUI-Icons-Brand.woff2",
    "/fonts/CoreUI-Icons-Free.eot": "/fonts/CoreUI-Icons-Free.eot",
    "/fonts/CoreUI-Icons-Free.svg": "/fonts/CoreUI-Icons-Free.svg",
    "/fonts/CoreUI-Icons-Free.ttf": "/fonts/CoreUI-Icons-Free.ttf",
    "/fonts/CoreUI-Icons-Free.woff": "/fonts/CoreUI-Icons-Free.woff",
    "/fonts/CoreUI-Icons-Free.woff2": "/fonts/CoreUI-Icons-Free.woff2",
    "/css/free.min.css": "/css/free.min.css",
    "/css/brand.min.css": "/css/brand.min.css",
    "/css/flag.min.css": "/css/flag.min.css"
}
